odoo/addons/role_policy_hr_expense/README.rst
odoo/addons/role_policy_hr_expense/__init__.py
odoo/addons/role_policy_hr_expense/__manifest__.py
odoo/addons/role_policy_hr_expense/i18n/role_policy_hr_expense.pot
odoo/addons/role_policy_hr_expense/models/__init__.py
odoo/addons/role_policy_hr_expense/models/base.py
odoo/addons/role_policy_hr_expense/readme/CONTRIBUTORS.rst
odoo/addons/role_policy_hr_expense/readme/DESCRIPTION.rst
odoo/addons/role_policy_hr_expense/static/description/icon.png
odoo/addons/role_policy_hr_expense/static/description/index.html
odoo/addons/role_policy_hr_expense/views/menu.xml
odoo13_addon_role_policy_hr_expense-13.0.1.1.0.dist-info/METADATA
odoo13_addon_role_policy_hr_expense-13.0.1.1.0.dist-info/WHEEL
odoo13_addon_role_policy_hr_expense-13.0.1.1.0.dist-info/top_level.txt
odoo13_addon_role_policy_hr_expense-13.0.1.1.0.dist-info/RECORD
